<!--
WARNING: THIS IS AN AUTO-GENERATED FILE. CHANGES TO IT ARE LIKELY TO BE
OVERWRITTEN AND LOST. Changes to this xml configuration should be made using:
  virsh pool-edit CentosRedhat
or other application using the libvirt API.
-->

<pool type='dir'>
  <name>CentosRedhat</name>
  <uuid>7b8b4a26-0919-4425-b18d-ff459c42f2ff</uuid>
  <capacity unit='bytes'>0</capacity>
  <allocation unit='bytes'>0</allocation>
  <available unit='bytes'>0</available>
  <source>
  </source>
  <target>
    <path>/home/sabbir/.local/share/libvirt/images/CentosRedhat</path>
  </target>
</pool>
